analytics_sdk/__init__.py
analytics_sdk/api_client.py
analytics_sdk/components.py
analytics_sdk/components_original.py
analytics_sdk/constants.py
analytics_sdk/oap_dash.py
analytics_sdk/oap_dash_original.py
analytics_sdk/utilities.py
analytics_sdk/analysis-wrapper/main.js
analytics_sdk/analysis-wrapper/main.wrapper.css
analytics_sdk/analysis-wrapper/main.wrapper.js
analytics_sdk/analysis-wrapper/media/close.82b1ae2d.svg
analytics_sdk/analysis-wrapper/media/fontello.487f60cd.woff
analytics_sdk/analysis-wrapper/media/fontello.52a41d35.svg
analytics_sdk/analysis-wrapper/media/fontello.8be26641.ttf
analytics_sdk/analysis-wrapper/media/fontello.8fcd07de.woff2
analytics_sdk/analysis-wrapper/media/fontello.d35868c4.eot
analytics_sdk/analysis-wrapper/media/icon-copy.c16adda9.svg
analytics_sdk/analysis-wrapper/media/icon-edit.ae3b1e05.svg
analytics_sdk/analysis-wrapper/media/icon-remove.184d1ffb.svg
analytics_sdk/analysis-wrapper/media/revicons.04eb8fc5.woff
analytics_sdk/analysis-wrapper/media/revicons.17629a5d.ttf
analytics_sdk/analysis-wrapper/media/revicons.2feb69cc.eot
analytics_sdk/analysis-wrapper/media/transparent-bg.5f803547.svg
analytics_sdk/process/__init__.py
analytics_sdk/process/process.py
analytics_sdk/process/querybuilder.py
analytics_sdk/renderer/__init__.py
analytics_sdk/renderer/excel.py
analytics_sdk/renderer/pdf.py
new_dash_opsramp_analytics_utils-1.1.2.dist-info/LICENSE
new_dash_opsramp_analytics_utils-1.1.2.dist-info/METADATA
new_dash_opsramp_analytics_utils-1.1.2.dist-info/WHEEL
new_dash_opsramp_analytics_utils-1.1.2.dist-info/top_level.txt
new_dash_opsramp_analytics_utils-1.1.2.dist-info/RECORD
