Metadata-Version: 2.1
Name: new-dash-opsramp-analytics-utils
Version: 1.1.2
Summary: OpsRamp Analytics SDK
Author: OpsRamp
Author-email: opsramp@support.com
Classifier: Programming Language :: Python :: 3
Classifier: License :: OSI Approved :: MIT License
Classifier: Operating System :: OS Independent
Requires-Python: >=3.6
License-File: LICENSE
Requires-Dist: boto3 ==1.17.51
Requires-Dist: botocore ==1.20.51
Requires-Dist: openpyxl ==3.0.7
Requires-Dist: flask ==3.0.0
Requires-Dist: dash ==2.14.2
Requires-Dist: requests ==2.31.0
Requires-Dist: Werkzeug ==3.0.1
Requires-Dist: urllib3 ==1.26.18
